Metadata-Version: 2.1
Name: SubFucker
Version: 1.0.2
Summary: SubFucker is simple tool designed to help bughunters with enumerating subdomain status codes
Home-page: https://github.com/TheXerr0r/SubFucker
Author: Scorpion Shiled
Author-email: support@scorpion-shield.com
License: UNKNOWN
Platform: UNKNOWN
Classifier: Programming Language :: Python :: 3
Classifier: Operating System :: OS Independent
Requires-Python: >=3.6
